molecule_schema/__init__.py
molecule_schema/base.py
molecule_schema/builtins.py
molecule_schema/predefined.py
molecule_schema/schema.py
molecule_schema/test_schema.py
molecule_schema/test_witness_args.py
molecule_schema/version.py
molecule_schema-0.1.1.dist-info/METADATA
molecule_schema-0.1.1.dist-info/WHEEL
molecule_schema-0.1.1.dist-info/top_level.txt
molecule_schema-0.1.1.dist-info/RECORD
