Metadata-Version: 2.1
Name: molecule-schema
Version: 0.1.1
Summary: Molecule Code First Schema
Home-page: https://github.com/doitian/molecule-schema-python
Author: ian
Author-email: ian@nervos.org
License: MIT
Classifier: Development Status :: 2 - Pre-Alpha
Classifier: Environment :: Console
Classifier: Topic :: File Formats
